[
  {
    "id": "1",
    "name": "Maple Leaf Books",
    "category": "books",
    "url": "https://mapleleafbooks.ca",
    "tags": [
      "independent",
      "reading",
      "canada"
    ]
  },
  {
    "id": "2",
    "name": "Northern Roast Coffee",
    "category": "beverages",
    "url": "https://northernroast.ca",
    "tags": [
      "coffee",
      "beans",
      "local"
    ]
  },
  {
    "id": "3",
    "name": "Green Meadow Dairy",
    "category": "dairy-free",
    "url": "https://greenmeadow.com",
    "tags": [
      "oat milk",
      "vegan",
      "oatmilk"
    ]
  },
  {
    "id": "4",
    "name": "EcoGrocery Co-op",
    "category": "groceries",
    "url": "https://ecogrocery.coop",
    "tags": [
      "oat milk",
      "organic",
      "honey"
    ]
  },
  {
    "id": "5",
    "name": "The Honeycomb",
    "category": "specialty",
    "url": "https://thehoneycomb.ca",
    "tags": [
      "honey",
      "apiary",
      "bees"
    ]
  },
  {
    "id": "6",
    "name": "Pastamore Local Wheat",
    "category": "pasta",
    "url": "https://pastamore.ca",
    "tags": [
      "pasta",
      "wheat",
      "local"
    ]
  },
  {
    "id": "7",
    "name": "Grain Mill Artisans",
    "category": "pasta/grains",
    "url": "https://grainmill.ca",
    "tags": [
      "pasta",
      "organic",
      "spaghetti"
    ]
  },
  {
    "id": "8",
    "name": "Sustainable Toys & Games",
    "category": "toys",
    "url": "https://sustainabletoys.com",
    "tags": [
      "toy car",
      "wooden toys",
      "eco-play"
    ]
  }
]